{
    "prepare_queue": {
        "installed": [],
        "uninstalled": []
    },
    "config_munge": {
        "files": {
            "framework": {
                "parents": {
                    "CoreBluetooth.framework": [
                        {
                            "xml": false,
                            "count": 1
                        }
                    ],
                    "CoreGraphics.framework": [
                        {
                            "xml": false,
                            "count": 6
                        }
                    ],
                    "ImageIO.framework": [
                        {
                            "xml": true,
                            "count": 1
                        }
                    ],
                    "CoreLocation.framework": [
                        {
                            "xml": false,
                            "count": 3
                        }
                    ],
                    "AssetsLibrary.framework": [
                        {
                            "xml": false,
                            "count": 3
                        }
                    ],
                    "MobileCoreServices.framework": [
                        {
                            "xml": false,
                            "count": 3
                        }
                    ],
                    "AddressBook.framework": [
                        {
                            "xml": true,
                            "count": 1
                        }
                    ],
                    "AddressBookUI.framework": [
                        {
                            "xml": true,
                            "count": 1
                        }
                    ],
                    "CoreMotion.framework": [
                        {
                            "xml": false,
                            "count": 1
                        }
                    ],
                    "AudioToolbox.framework": [
                        {
                            "xml": true,
                            "count": 2
                        }
                    ],
                    "SystemConfiguration.framework": [
                        {
                            "xml": true,
                            "count": 1
                        }
                    ],
                    "Security.framework": [
                        {
                            "xml": false,
                            "count": 1
                        }
                    ],
                    "CFNetwork.framework": [
                        {
                            "xml": false,
                            "count": 1
                        }
                    ]
                }
            },
            "config.xml": {
                "parents": {
                    "/widget": [
                        {
                            "xml": "<feature name=\"BLE\"><param name=\"ios-package\" onload=\"true\" value=\"BLECentralPlugin\" /></feature>",
                            "count": 1
                        },
                        {
                            "xml": "<feature name=\"IosSocketsCommon\"><param name=\"ios-package\" value=\"IosSocketsCommon\" /></feature>",
                            "count": 1
                        },
                        {
                            "xml": "<feature name=\"ChromeSocketsUdp\"><param name=\"ios-package\" value=\"ChromeSocketsUdp\" /></feature>",
                            "count": 1
                        }
                    ],
                    "/*": [
                        {
                            "xml": "<feature name=\"Device\"><param name=\"ios-package\" value=\"CDVDevice\" /></feature>",
                            "count": 1
                        },
                        {
                            "xml": "<feature name=\"InAppBrowser\"><param name=\"ios-package\" value=\"CDVInAppBrowser\" /></feature>",
                            "count": 1
                        },
                        {
                            "xml": "<feature name=\"Battery\"><param name=\"ios-package\" value=\"CDVBattery\" /></feature>",
                            "count": 1
                        },
                        {
                            "xml": "<feature name=\"Camera\"><param name=\"ios-package\" value=\"CDVCamera\" /></feature>",
                            "count": 1
                        },
                        {
                            "xml": "<preference name=\"CameraUsesGeolocation\" value=\"false\" />",
                            "count": 1
                        },
                        {
                            "xml": "<feature name=\"Console\"><param name=\"ios-package\" value=\"CDVLogger\" /></feature>",
                            "count": 1
                        },
                        {
                            "xml": "<feature name=\"Contacts\"><param name=\"ios-package\" value=\"CDVContacts\" /></feature>",
                            "count": 1
                        },
                        {
                            "xml": "<feature name=\"Accelerometer\"><param name=\"ios-package\" value=\"CDVAccelerometer\" /></feature>",
                            "count": 1
                        },
                        {
                            "xml": "<feature name=\"Compass\"><param name=\"ios-package\" value=\"CDVCompass\" /></feature>",
                            "count": 1
                        },
                        {
                            "xml": "<feature name=\"Notification\"><param name=\"ios-package\" value=\"CDVNotification\" /></feature>",
                            "count": 1
                        },
                        {
                            "xml": "<feature name=\"File\"><param name=\"ios-package\" value=\"CDVFile\" /><param name=\"onload\" value=\"true\" /></feature>",
                            "count": 1
                        },
                        {
                            "xml": "<feature name=\"FileTransfer\"><param name=\"ios-package\" value=\"CDVFileTransfer\" /></feature>",
                            "count": 1
                        },
                        {
                            "xml": "<feature name=\"Geolocation\"><param name=\"ios-package\" value=\"CDVLocation\" /></feature>",
                            "count": 1
                        },
                        {
                            "xml": "<feature name=\"Globalization\"><param name=\"ios-package\" value=\"CDVGlobalization\" /></feature>",
                            "count": 1
                        },
                        {
                            "xml": "<feature name=\"Media\"><param name=\"ios-package\" value=\"CDVSound\" /></feature>",
                            "count": 1
                        },
                        {
                            "xml": "<feature name=\"Capture\"><param name=\"ios-package\" value=\"CDVCapture\" /></feature>",
                            "count": 1
                        },
                        {
                            "xml": "<feature name=\"NetworkStatus\"><param name=\"ios-package\" value=\"CDVConnection\" /></feature>",
                            "count": 1
                        },
                        {
                            "xml": "<feature name=\"SplashScreen\"><param name=\"ios-package\" value=\"CDVSplashScreen\" /><param name=\"onload\" value=\"true\" /></feature>",
                            "count": 1
                        },
                        {
                            "xml": "<feature name=\"StatusBar\"><param name=\"ios-package\" value=\"CDVStatusBar\" /><param name=\"onload\" value=\"true\" /></feature>",
                            "count": 1
                        },
                        {
                            "xml": "<preference name=\"StatusBarOverlaysWebView\" value=\"true\" />",
                            "count": 1
                        },
                        {
                            "xml": "<preference name=\"StatusBarStyle\" value=\"lightcontent\" />",
                            "count": 1
                        },
                        {
                            "xml": "<feature name=\"Vibration\"><param name=\"ios-package\" value=\"CDVVibration\" /></feature>",
                            "count": 1
                        },
                        {
                            "xml": "<feature name=\"Discovery\"><param name=\"ios-package\" value=\"CDVDiscovery\" /><param name=\"onload\" value=\"true\" /></feature>",
                            "count": 1
                        }
                    ]
                }
            },
            "*-Info.plist": {
                "parents": {
                    "NSLocationWhenInUseUsageDescription": [
                        {
                            "xml": "<string />",
                            "count": 2
                        }
                    ]
                }
            }
        }
    },
    "installed_plugins": {
        "com.megster.cordova.ble": {
            "PACKAGE_NAME": "edu.umich.eecs.lab11.summon"
        },
        "cordova-plugin-whitelist": {
            "PACKAGE_NAME": "edu.umich.eecs.lab11.summon"
        },
        "cordova-plugin-device": {
            "PACKAGE_NAME": "edu.umich.eecs.lab11.summon"
        },
        "cordova-plugin-inappbrowser": {
            "PACKAGE_NAME": "edu.umich.eecs.lab11.summon"
        },
        "cordova-plugin-battery-status": {
            "PACKAGE_NAME": "edu.umich.eecs.lab11.summon"
        },
        "cordova-plugin-camera": {
            "PACKAGE_NAME": "edu.umich.eecs.lab11.summon"
        },
        "cordova-plugin-console": {
            "PACKAGE_NAME": "edu.umich.eecs.lab11.summon"
        },
        "cordova-plugin-contacts": {
            "PACKAGE_NAME": "edu.umich.eecs.lab11.summon"
        },
        "cordova-plugin-device-motion": {
            "PACKAGE_NAME": "edu.umich.eecs.lab11.summon"
        },
        "cordova-plugin-device-orientation": {
            "PACKAGE_NAME": "edu.umich.eecs.lab11.summon"
        },
        "cordova-plugin-dialogs": {
            "PACKAGE_NAME": "edu.umich.eecs.lab11.summon"
        },
        "cordova-plugin-file": {
            "PACKAGE_NAME": "edu.umich.eecs.lab11.summon"
        },
        "cordova-plugin-file-transfer": {
            "PACKAGE_NAME": "edu.umich.eecs.lab11.summon"
        },
        "cordova-plugin-geolocation": {
            "PACKAGE_NAME": "edu.umich.eecs.lab11.summon"
        },
        "cordova-plugin-globalization": {
            "PACKAGE_NAME": "edu.umich.eecs.lab11.summon"
        },
        "cordova-plugin-legacy-whitelist": {
            "PACKAGE_NAME": "edu.umich.eecs.lab11.summon"
        },
        "cordova-plugin-media": {
            "PACKAGE_NAME": "edu.umich.eecs.lab11.summon"
        },
        "cordova-plugin-media-capture": {
            "PACKAGE_NAME": "edu.umich.eecs.lab11.summon"
        },
        "cordova-plugin-network-information": {
            "PACKAGE_NAME": "edu.umich.eecs.lab11.summon"
        },
        "cordova-plugin-splashscreen": {
            "PACKAGE_NAME": "edu.umich.eecs.lab11.summon"
        },
        "cordova-plugin-statusbar": {
            "PACKAGE_NAME": "edu.umich.eecs.lab11.summon"
        },
        "cordova-plugin-test-framework": {
            "PACKAGE_NAME": "edu.umich.eecs.lab11.summon"
        },
        "cordova-plugin-vibration": {
            "PACKAGE_NAME": "edu.umich.eecs.lab11.summon"
        },
        "cordova-plugin-chrome-apps-sockets-udp": {
            "PACKAGE_NAME": "edu.umich.eecs.lab11.summon"
        },
        "com.ionicsdk.discovery": {
            "PACKAGE_NAME": "edu.umich.eecs.lab11.summon"
        }
    },
    "dependent_plugins": {
        "cordova-plugin-chrome-apps-common": {
            "PACKAGE_NAME": "edu.umich.eecs.lab11.summon"
        },
        "cordova-plugin-chrome-apps-iossocketscommon": {
            "PACKAGE_NAME": "edu.umich.eecs.lab11.summon"
        }
    }
}